{
  "entry": {
    "locale": "fr-ca",
    "ad_content": [
      {
        "ad_builder_block": {
          "ad_builder_ref": [
            {
              "_content_type_uid": "ad_builder",
              "entry": {
                "locale": "fr-ca",
                "ad_type": "half",
                "background_group": {
                  "background_gradient_style": "solid",
                  "background_color": {
                    "hex": "#FFFFFF"
                  },
                  "background_gradient_color": {
                    "color1": {
                      "hex": ""
                    },
                    "color2": {
                      "hex": ""
                    }
                  },
                  "text_color": {
                    "hex": ""
                  },
                  "border_color_type": "no-border",
                  "border_color": {
                    "solid": {
                      "hex": ""
                    },
                    "shadow": {
                      "hex": ""
                    }
                  }
                },
                "caption": "",
                "costco_url": {
                  "title": "Histoire de Barbie",
                  "url": "",
                  "external_site": false,
                  "same_tab_domain": true,
                  "reference_link": false,
                  "content_type_uid": "",
                  "entry_title": "",
                  "entry_uid": "",
                  "page_id": "",
                  "open_as_pop_up": false
                },
                "disclaimer": "",
                "disclaimer_markdown": "",
                "enable_caption": false,
                "enable_custom_background": true,
                "enable_disclaimer": false,
                "enable_mobile_image_variation": false,
                "enable_product_linked": false,
                "enable_sponsored": false,
                "enable_text_content": true,
                "image": [
                  {
                    "id": "7btmkvsm748cfcpqj457vb",
                    "name": "09_23_Costco_Life_04.jpg",
                    "position": 0,
                    "type": "attachments",
                    "url": "https://cdn.bfldr.com/56O3HXZ9/at/7btmkvsm748cfcpqj457vb/09_23_Costco_Life_04.jpg?auto=webp&format=jpg",
                    "filename": "09_23_Costco_Life_04.jpg",
                    "extension": "jpg",
                    "mimetype": "image/jpeg",
                    "thumbnailUrl": "https://thumbs.bfldr.com/at/7btmkvsm748cfcpqj457vb/v/1302021434?expiry=1773838800&fit=bounds&height=162&sig=ZDYxZDk4ZGFiMDg3NTI2NTdiZmUzODZmYWU2NjkzM2QxYWQ2ZWZmNA%3D%3D&width=262",
                    "dimensions": {
                      "width": 800,
                      "height": 700,
                      "type": 0
                    }
                  }
                ],
                "image_alt_text": "Barbie playhouse",
                "mobile_image": [],
                "mobile_image_alt_text": "",
                "platform_config_block": {
                  "platform_aplicability": "mobile_web",
                  "ios_version_support": "",
                  "android_version_support": ""
                },
                "privacy_toggle": {
                  "disable_third_party_tracking": false
                },
                "product_link": {},
                "tags": [
                  "migrated-from-cms"
                ],
                "text_content": [
                  {
                    "markdown_text": {
                      "select_text_type": "caption_v2",
                      "select_semantics_type": null,
                      "markdown_text": "LA MARQUE BARBIE CONTINUE À ÉVOLUER.  \n",
                      "color": {
                        "background_gradient_style": "no-background",
                        "background_color": {
                          "hex": ""
                        },
                        "background_gradient_color": {
                          "color1": {
                            "hex": ""
                          },
                          "color2": {
                            "hex": ""
                          }
                        },
                        "text_color": {
                          "hex": "#333333"
                        },
                        "border_color_type": "no-border",
                        "border_color": {
                          "solid": {
                            "hex": ""
                          },
                          "shadow": {
                            "hex": ""
                          }
                        }
                      }
                    }
                  },
                  {
                    "markdown_text": {
                      "select_text_type": "body_copy_v2",
                      "select_semantics_type": null,
                      "markdown_text": "AU FIL DES ÂGES  \n",
                      "color": {
                        "text_color": {
                          "hex": "#b01c33"
                        },
                        "background_gradient_style": "solid",
                        "background_color": {
                          "hex": "#ffffff"
                        },
                        "border_color_type": "no-border",
                        "border_color": {
                          "solid": {
                            "hex": "#cccccc"
                          },
                          "shadow": {
                            "hex": "#cccccc"
                          }
                        }
                      }
                    }
                  },
                  {
                    "markdown_text": {
                      "select_text_type": "subheading_v2",
                      "select_semantics_type": "h3",
                      "markdown_text": "**Histoire de Barbie**",
                      "color": {
                        "background_gradient_style": "solid",
                        "background_color": {
                          "hex": "#FFFFFF"
                        },
                        "background_gradient_color": {
                          "color1": {
                            "hex": ""
                          },
                          "color2": {
                            "hex": ""
                          }
                        },
                        "text_color": {
                          "hex": "#333333"
                        },
                        "border_color_type": "no-border",
                        "border_color": {
                          "solid": {
                            "hex": "#cccccc"
                          },
                          "shadow": {
                            "hex": "#cccccc"
                          }
                        }
                      }
                    }
                  },
                  {
                    "markdown_text": {
                      "select_text_type": "body_copy_v2",
                      "select_semantics_type": null,
                      "markdown_text": "Fondée en 1959 par Ruth Handler, Barbie a évolué au fil des ans. Voici quelques faits sur la poupée de Barbiemedia.com*. Les entrepôts Costco et Costco.ca offrent des jouets Barbie.\n\n- Barbie et Ken ont été nommés en l'honneur des enfants de Mme Handler, Barbara et Kenneth.  \n- La poupée est d'abord apparue portant son maillot de bain rayé noir et blanc emblématique.  \n- La mannequin britannique Twiggy a inspiré la première poupée de célébrité Barbie en 1967.  \n- En appui aux droits à l'égalité, Barbie a lancé Christie, l'une des premières poupées noires, en 1968.  \n- Barbie a eu plus de 200 carrières, notamment astronaute, pilote, pompière, journaliste et entrepreneure.  \n- Plus de 100 poupées sont achetées chaque minute, totalisant 58 millions chaque année dans 150 pays.  ",
                      "color": {
                        "background_gradient_style": "solid",
                        "background_color": {
                          "hex": "#FFFFFF"
                        },
                        "background_gradient_color": {
                          "color1": {
                            "hex": ""
                          },
                          "color2": {
                            "hex": ""
                          }
                        },
                        "text_color": {
                          "hex": "#333333"
                        },
                        "border_color_type": "no-border",
                        "border_color": {
                          "solid": {
                            "hex": "#cccccc"
                          },
                          "shadow": {
                            "hex": "#cccccc"
                          }
                        }
                      }
                    }
                  }
                ],
                "text_content_above_below_the_ad_styles": [
                  {
                    "above_below_the_ad_styles": {
                      "text_alignment": "left"
                    }
                  }
                ],
                "text_content_overlay_styles": [
                  {
                    "overlay_style": {
                      "applicability": "default",
                      "overlay_fill_type": "horizontal",
                      "overlay_fill_": "100",
                      "overlay_position": "top",
                      "text_alignment": "middle",
                      "overlay_background_color": {}
                    }
                  }
                ],
                "text_content_placement": "below_the_ad",
                "title": "History of Barbie - 1759225400001",
                "top_and_bottom_strip": [],
                "top_and_bottom_text_banner": [],
                "use_mobile_image_alt_text": false
              }
            }
          ]
        }
      }
    ],
    "ad_set_background": {
      "title_background_color": {},
      "title_background_transparency": "1",
      "body_background_color": {},
      "body_background_transparency": "1"
    },
    "ad_set_heading_and_costco_url": {
      "title": "",
      "url": "",
      "external_site": false,
      "reference_link": false,
      "content_type_uid": "",
      "entry_title": "",
      "entry_uid": "",
      "page_id": "",
      "open_as_pop_up": false
    },
    "ad_set_style": "static",
    "background_foreground_banner_group": {
      "background_banner_button_alignment": "horizontal",
      "background_banner_image_alignment": "top",
      "background_banner_reference": [],
      "foreground_banner_group": []
    },
    "caption": "",
    "category_content": {
      "category_items": [],
      "image_form_factor": "rounded",
      "background_color": {},
      "category_set_title_alignment": "left",
      "category_content_placement": null
    },
    "custom_background": false,
    "enable_background_foreground_banner": false,
    "item_type": "ad",
    "platform_config_block": {
      "android_version_support": "",
      "ios_version_support": "",
      "platform_aplicability": "mobile_web"
    },
    "product_content": {
      "product_list": {}
    },
    "product_display_style": {
      "product_card_display_style": "compact",
      "show_action_button": true,
      "show_reviews": true,
      "inventory_aware_listings": false,
      "product_tile_data_source": null
    },
    "rotating_options": {
      "multi_item_carousel": false,
      "enable_autoplay": false,
      "enable_two_row_display": false,
      "randomize_items": false,
      "enable_peek_a_boo": false
    },
    "static_options": {
      "display_style": "multi_row",
      "maximum_tiles_per_row": 5
    },
    "tags": [
      "migrated-from-cms"
    ],
    "title": "History of Barbie - 1759225400000 - 1765187374525"
  }
}